polars_s2-0.1.0.dist-info/METADATA
polars_s2-0.1.0.dist-info/WHEEL
polars_s2-0.1.0.dist-info/license_files/LICENSE
polars_s2/__init__.py
polars_s2/polars_s2.pypy39-pp73-s390x-linux-gnu.so
polars_s2-0.1.0.dist-info/RECORD
