Metadata-Version: 2.1
Name: polars-s2
Version: 0.1.0
Classifier: Programming Language :: Rust
Classifier: Programming Language :: Python :: Implementation :: CPython
Classifier: Programming Language :: Python :: Implementation :: PyPy
License-File: LICENSE
Summary: Polars plugin for S2 Cell.
Author-email: Tyler Anderson <31015976+tylanderson@users.noreply.github.com>
Requires-Python: >=3.8
